[
  {
    "imageId": 0
  },
  {
    "imageId": 1
  },
  {
    "imageId": 2
  },
  {
    "imageId": 3
  },
  {
    "imageId": 4
  },
  {
    "imageId": 5
  },
  {
    "imageId": 6,
    "health": 130,
    "types": [
      "INSECT"
    ]
  },
  {
    "imageId": 7
  },
  {
    "imageId": 8
  },
  {
    "imageId": 9
  },
  {
    "imageId": 10
  },
  {
    "imageId": 11
  },
  {
    "imageId": 12,
    "health": 300,
    "organs": {
      "122": "1",
      "123": "1",
      "124": "1",
      "125": "1",
      "126": "1",
      "127": "2-4",
      "128": "6-8",
      "129": "2",
      "130": "8-12",
      "131": "5-10",
      "133": "1"
    },
    "bloodType": "BLOOD"
  },
  {
    "imageId": 13
  },
  {
    "imageId": 14
  },
  {
    "imageId": 15
  },
  {
    "imageId": 16
  },
  {
    "imageId": 17
  },
  {
    "imageId": 18
  },
  {
    "imageId": 19
  },
  {
    "imageId": 20,
    "types": [
      "INSECT"
    ]
  },
  {
    "imageId": 21,
    "types": [
      "INSECT"
    ]
  },
  {
    "imageId": 22
  },
  {
    "imageId": 23
  },
  {
    "imageId": 24
  },
  {
    "imageId": 25
  },
  {
    "imageId": 26,
    "types": [
      "INSECT"
    ]
  },
  {
    "imageId": 27,
    "types": [
      "INSECT"
    ]
  },
  {
    "imageId": 28
  },
  {
    "imageId": 29
  },
  {
    "imageId": 30
  },
  {
    "imageId": 31
  },
  {
    "imageId": 32
  },
  {
    "imageId": 33
  },
  {
    "imageId": 34
  },
  {
    "imageId": 35
  },
  {
    "imageId": 36
  },
  {
    "imageId": 37
  },
  {
    "imageId": 38
  },
  {
    "imageId": 39,
    "types": [
      "INSECT"
    ]
  },
  {
    "imageId": 40,
    "types": [
      "INSECT"
    ]
  },
  {
    "imageId": 41,
    "types": [
      "INSECT"
    ]
  },
  {
    "imageId": 42,
    "types": [
      "INSECT"
    ]
  },
  {
    "imageId": 43,
    "types": [
      "INSECT"
    ]
  },
  {
    "imageId": 44
  },
  {
    "imageId": 45
  },
  {
    "imageId": 46
  },
  {
    "imageId": 47,
    "types": [
      "INSECT"
    ]
  },
  {
    "imageId": 48,
    "types": [
      "INSECT"
    ]
  },
  {
    "imageId": 49,
    "types": [
      "INSECT"
    ]
  },
  {
    "imageId": 50,
    "types": [
      "INSECT"
    ]
  },
  {
    "imageId": 51
  },
  {
    "imageId": 52
  },
  {
    "imageId": 53
  },
  {
    "imageId": 54
  },
  {
    "imageId": 55
  },
  {
    "imageId": 56
  },
  {
    "imageId": 57
  },
  {
    "imageId": 58
  },
  {
    "imageId": 59
  },
  {
    "imageId": 60
  },
  {
    "imageId": 61
  },
  {
    "imageId": 62
  },
  {
    "imageId": 63
  },
  {
    "imageId": 64
  },
  {
    "imageId": 65
  },
  {
    "imageId": 66
  },
  {
    "imageId": 67
  },
  {
    "imageId": 68
  },
  {
    "imageId": 69
  },
  {
    "imageId": 70
  },
  {
    "imageId": 71
  },
  {
    "imageId": 72
  },
  {
    "imageId": 73
  },
  {
    "imageId": 74
  },
  {
    "imageId": 75
  },
  {
    "imageId": 76
  },
  {
    "imageId": 77,
    "health": 200,
    "organs": {
      "129": "4-12",
      "137": "5-10",
      "120": "0-2"
    },
    "bloodType": "BLOOD"
  },
  {
    "imageId": 78,
    "health": 60,
    "organs": {
      "129": "3-8",
      "137": "2-5",
      "120": "0-1"
    },
    "bloodType": "BLOOD"
  },
  {
    "imageId": 79,
    "health": 20,
    "organs": {
      "129": "2",
      "137": "1-2"
    },
    "bloodType": "BLOOD"
  },
  {
    "imageId": 80,
    "health": 80,
    "organs": {
      "129": "2",
      "137": "2-6",
      "120": "0-1"
    },
    "bloodType": "BLOOD"
  },
  {
    "imageId": 81,
    "health": 80,
    "organs": {
      "129": "2-4",
      "137": "2-6",
      "120": "0-1"
    },
    "bloodType": "BLOOD"
  },
  {
    "imageId": 82,
    "health": 40,
    "organs": {
      "129": "3",
      "137": "2-4",
      "120": "0-1"
    },
    "bloodType": "BLOOD"
  },
  {
    "imageId": 83,
    "health": 60,
    "organs": {
      "129": "2-4",
      "137": "2-6",
      "120": "0-1"
    },
    "bloodType": "BLOOD"
  },
  {
    "imageId": 84,
    "health": 450,
    "organs": {
      "129": "4-8",
      "137": "6-12",
      "127": "4-8",
      "120": "1-3"
    },
    "bloodType": "BLOOD"
  },
  {
    "imageId": 85
  },
  {
    "imageId": 86
  },
  {
    "imageId": 87
  },
  {
    "imageId": 88
  },
  {
    "imageId": 89
  },
  {
    "imageId": 90
  },
  {
    "imageId": 91
  },
  {
    "imageId": 92
  },
  {
    "imageId": 93
  },
  {
    "imageId": 94
  },
  {
    "imageId": 95
  },
  {
    "imageId": 96
  },
  {
    "imageId": 97
  },
  {
    "imageId": 98
  },
  {
    "imageId": 99
  },
  {
    "imageId": 100
  },
  {
    "imageId": 101,
    "health": 100,
    "bloodType": "BLOOD"
  },
  {
    "imageId": 102
  },
  {
    "imageId": 103
  },
  {
    "imageId": 104
  },
  {
    "imageId": 105
  },
  {
    "imageId": 106
  },
  {
    "imageId": 107
  },
  {
    "imageId": 108
  },
  {
    "imageId": 109
  },
  {
    "imageId": 110
  },
  {
    "imageId": 111
  },
  {
    "imageId": 112
  },
  {
    "imageId": 113
  },
  {
    "imageId": 114
  },
  {
    "imageId": 115
  },
  {
    "imageId": 116,
    "health": 200,
    "organs": {
      "136": "5-10"
    },
    "bloodType": "DIRT"
  },
  {
    "imageId": 117
  },
  {
    "imageId": 118
  },
  {
    "imageId": 119
  },
  {
    "imageId": 120
  },
  {
    "imageId": 121
  },
  {
    "imageId": 122
  },
  {
    "imageId": 123
  },
  {
    "imageId": 124
  },
  {
    "imageId": 125
  },
  {
    "imageId": 126
  },
  {
    "imageId": 127
  },
  {
    "imageId": 128
  },
  {
    "imageId": 129
  },
  {
    "imageId": 130
  },
  {
    "imageId": 131
  },
  {
    "imageId": 132
  },
  {
    "imageId": 133
  }
]